tubes.cp37-win_amd64.pyd
pytubes-0.8.1.dist-info/LICENSE
pytubes-0.8.1.dist-info/METADATA
pytubes-0.8.1.dist-info/WHEEL
pytubes-0.8.1.dist-info/top_level.txt
pytubes-0.8.1.dist-info/RECORD
