Metadata-Version: 2.1
Name: pytubes
Version: 0.8.1
Summary: A library for efficiently loading data into Python
Home-page: https://github.com/stestagg/pytubes
Author: Stephen Stagg
Author-email: stestagg@gmail.com
License: MIT
Platform: UNKNOWN
Classifier: License :: OSI Approved :: MIT License
Classifier: Programming Language :: Python
Classifier: Programming Language :: Python :: 3
Classifier: Programming Language :: Python :: 3.7
Classifier: Programming Language :: Python :: 3.6
Classifier: Programming Language :: Python :: 3.4
Classifier: Programming Language :: Python :: 3.5
Classifier: Programming Language :: Python :: Implementation :: CPython
Requires-Python: >=3.4.0
Requires-Dist: numpy
